Workbook

Sheet Dashboard
A1: Portfolio Dashboard V2
A2: Pure .xlsx dashboard generated from daily-average history
A4: Total Net Worth (IRT) | D4: Total Net Worth (USD) | H4: Latest Date | K4: USD Rate
A5: 23987529210 | D5: 124030.66 | H5: =History_Data!A115 | K5: =Live_Data!B4
A8: Owner Split | H8: Latest Prices
A9: Owner | B9: IRT | C9: USD | D9: Share | H9: Asset | I9: Price | J9: Unit
A10: Mother | B10: 12172999210 | C10: 62942.085 | D10: =IFERROR(B10/A5,0) | H10: =Live_Data!A2 | I10: =Live_Data!B2 | J10: =Live_Data!C2
A11: Father | B11: 11814530000 | C11: 61088.573 | D11: =IFERROR(B11/A5,0) | H11: =Live_Data!A3 | I11: =Live_Data!B3 | J11: =Live_Data!C3
H12: =Live_Data!A4 | I12: =Live_Data!B4 | J12: =Live_Data!C4
H13: =Live_Data!A5 | I13: =Live_Data!B5 | J13: =Live_Data!C5
A14: Asset-Class Allocation | H14: =Live_Data!A6 | I14: =Live_Data!B6 | J14: =Live_Data!C6
A15: Class | B15: IRT | C15: USD | D15: IRT Share | E15: USD Share | H15: =Live_Data!A7 | I15: =Live_Data!B7 | J15: =Live_Data!C7
A16: Gold | B16: 8575129210 | C16: 44338.827 | D16: =IFERROR(B16/A5,0) | E16: =IFERROR(C16/D5,0) | H16: =Live_Data!A8 | I16: =Live_Data!B8 | J16: =Live_Data!C8
A17: Cash | B17: 676900000 | C17: 3500 | D17: =IFERROR(B17/A5,0) | E17: =IFERROR(C17/D5,0) | H17: =Live_Data!A9 | I17: =Live_Data!B9 | J17: =Live_Data!C9
A18: Stock | B18: 7017500000 | C18: 36284.902 | D18: =IFERROR(B18/A5,0) | E18: =IFERROR(C18/D5,0) | H18: =Live_Data!A10 | I18: =Live_Data!B10 | J18: =Live_Data!C10
A19: Real Estate | B19: 7718000000 | C19: 39906.929 | D19: =IFERROR(B19/A5,0) | E19: =IFERROR(C19/D5,0) | H19: =Live_Data!A11 | I19: =Live_Data!B11 | J19: =Live_Data!C11
A20: Crypto | B20: 0 | C20: 0 | D20: =IFERROR(B20/A5,0) | E20: =IFERROR(C20/D5,0) | H20: =Live_Data!A12 | I20: =Live_Data!B12 | J20: =Live_Data!C12
H21: =Live_Data!A13 | I21: =Live_Data!B13 | J21: =Live_Data!C13
H22: =Live_Data!A14 | I22: =Live_Data!B14 | J22: =Live_Data!C14

Sheet Settings
A1: Setting | B1: Value | C1: Notes
A2: Rolling Window | B2: 30 | C2: Trend rows shown in charts; use All for full history
A3: Selected Currency | B3: IRT | C3: IRT or USD
A4: Comparison Start Date | B4: =IFERROR(INDEX(History_Data!A:A,MAX(2,COUNTA(History_Data!A:A)-29)),TODAY()) | C4: Editable
A5: Investment Amount | B5: 100000000 | C5: Editable lump-sum amount in asset currency
A6: Last Generated | B6: 46221.72 | C6: Local machine time

Sheet History_Data
A1: Date | B1: IRT_Mother_Gold | C1: IRT_Mother_Cash | D1: IRT_Mother_Stock | E1: IRT_Mother_RealEstate | F1: IRT_Mother_Crypto | G1: IRT_Father_Gold | H1: IRT_Father_Cash | I1: IRT_Father_Stock | J1: IRT_Father_RealEstate | K1: IRT_Father_Crypto | L1: IRT_Total_Gold | M1: IRT_Total_Cash | N1: IRT_Total_Stock | O1: IRT_Total_RealEstate | P1: IRT_Total_Crypto | Q1: USD_Mother_Gold | R1: USD_Mother_Cash | S1: USD_Mother_Stock | T1: USD_Mother_RealEstate | U1: USD_Mother_Crypto | V1: USD_Father_Gold | W1: USD_Father_Cash | X1: USD_Father_Stock | Y1: USD_Father_RealEstate | Z1: USD_Father_Crypto | AA1: USD_Total_Gold | AB1: USD_Total_Cash | AC1: USD_Total_Stock | AD1: USD_Total_RealEstate | AE1: USD_Total_Crypto | AF1: Price_bitcoin_usd | AG1: Price_usdt_irt | AH1: Price_usd_cash | AI1: Price_emami_coin | AJ1: Price_half_coin | AK1: Price_quarter_coin | AL1: Price_quarter_coin_pre86 | AM1: Price_swiss_gold_bar_1g | AN1: Price_swiss_gold_bar_2_5g | AO1: Price_one_gram_coin | AP1: Price_gold_18k_gram | AQ1: Price_kama_stock | AR1: Price_euro_cash | AS1: Price_gold_ounce_usd
A2: 46057 | B2: 4423820426 | C2: 78425000 | D2: 0 | E2: 7718000000 | F2: 0 | G2: 4357500000 | H2: 470550000 | I2: 6572500000 | J2: 0 | K2: 0 | L2: 8781320426 | M2: 548975000 | N2: 6572500000 | O2: 7718000000 | P2: 0 | Q2: 27401.069 | R2: 485.7631 | S2: 0 | T2: 47805.162 | U2: 0 | V2: 26990.282 | W2: 2914.5788 | X2: 40709.954 | Y2: 0 | Z2: 0 | AA2: 54391.351 | AB2: 3400.3419 | AC2: 40709.954 | AD2: 47805.162 | AE2: 0 | AF2: 73000 | AG2: 161447 | AH2: 156850 | AI2: 194500000 | AJ2: 100500000 | AK2: 57500000 | AL2: 42128713 | AM2: 25900000 | AN2: 61610000 | AO2: 27500000 | AP2: 19172200 | AQ2: 2629 | AR2: 185380 | AS2: 4906
A3: 46058 | B3: 4.4623227e+09 | C3: 81129722 | D3: 0 | E3: 7718000000 | F3: 0 | G3: 4.3984011e+09 | H3: 4.8677833e+08 | I3: 6572500000 | J3: 0 | K3: 0 | L3: 8.8607238e+09 | M3: 5.6790806e+08 | N3: 6572500000 | O3: 7718000000 | P3: 0 | Q3: 27315.214 | R3: 496.6193 | S3: 0 | T3: 47244.191 | U3: 0 | V3: 26923.931 | W3: 2979.7161 | X3: 40232.242 | Y3: 0 | Z3: 0 | AA3: 54239.145 | AB3: 3476.3354 | AC3: 40232.242 | AD3: 47244.191 | AE3: 0 | AF3: 69515.196 | AG3: 163364 | AH3: 162259.44 | AI3: 1.9650222e+08 | AJ3: 1.0235444e+08 | AK3: 56500000 | AL3: 49121718 | AM3: 25900000 | AN3: 61610000 | AO3: 27500000 | AP3: 19357133 | AQ3: 2629 | AR3: 191536.67 | AS3: 4848.2222
A4: 46059 | B4: 4413420936 | C4: 81120000 | D4: 0 | E4: 7718000000 | F4: 0 | G4: 4375400000 | H4: 486720000 | I4: 6572500000 | J4: 0 | K4: 0 | L4: 8788820936 | M4: 567840000 | N4: 6572500000 | O4: 7718000000 | P4: 0 | Q4: 26857.879 | R4: 493.6559 | S4: 0 | T4: 46967.899 | U4: 0 | V4: 26626.502 | W4: 2961.9352 | X4: 39996.957 | Y4: 0 | Z4: 0 | AA4: 53484.381 | AB4: 3455.5911 | AC4: 39996.957 | AD4: 46967.899 | AE4: 0 | AF4: 67939.871 | AG4: 164325 | AH4: 162240 | AI4: 195500000 | AJ4: 100400000 | AK4: 56500000 | AL4: 49121718 | AM4: 25900000 | AN4: 61610000 | AO4: 27500000 | AP4: 19066833 | AQ4: 2629 | AR4: 191560 | AS4: 4938.2667
A5: 46060 | B5: 4.3321529e+09 | C5: 79289167 | D5: 0 | E5: 7718000000 | F5: 0 | G5: 4227730000 | H5: 475735000 | I5: 6720000000 | J5: 0 | K5: 0 | L5: 8.5598829e+09 | M5: 5.5502417e+08 | N5: 6720000000 | O5: 7718000000 | P5: 0 | Q5: 26860.235 | R5: 491.6091 | S5: 0 | T5: 47853.179 | U5: 0 | V5: 26212.791 | W5: 2949.6543 | X5: 41665.375 | Y5: 0 | Z5: 0 | AA5: 53073.026 | AB5: 3441.2634 | AC5: 41665.375 | AD5: 47853.179 | AE5: 0 | AF5: 68078.52 | AG5: 161285 | AH5: 158578.33 | AI5: 1.8866333e+08 | AJ5: 99300000 | AK5: 55500000 | AL5: 48252307 | AM5: 25900000 | AN5: 61610000 | AO5: 26500000 | AP5: 18699000 | AQ5: 2688 | AR5: 187436.67 | AS5: 4961
A6: 46061 | B6: 4309543924 | C6: 78675000 | D6: 0 | E6: 7718000000 | F6: 0 | G6: 4214105000 | H6: 472050000 | I6: 6515000000 | J6: 0 | K6: 0 | L6: 8523648924 | M6: 550725000 | N6: 6515000000 | O6: 7718000000 | P6: 0 | Q6: 26854.757 | R6: 490.2602 | S6: 0 | T6: 48094.419 | U6: 0 | V6: 26260.033 | W6: 2941.5614 | X6: 40597.971 | Y6: 0 | Z6: 0 | AA6: 53114.789 | AB6: 3431.8216 | AC6: 40597.971 | AD6: 48094.419 | AE6: 0 | AF6: 70669.86 | AG6: 160476 | AH6: 157350 | AI6: 188340000 | AJ6: 95900000 | AK6: 54355000 | AL6: 47256831 | AM6: 25900000 | AN6: 61610000 | AO6: 26836878 | AP6: 18623350 | AQ6: 2606 | AR6: 185985 | AS6: 4961
A7: 46062 | B7: 4.4145419e+09 | C7: 80303333 | D7: 0 | E7: 7718000000 | F7: 0 | G7: 4332535000 | H7: 481820000 | I7: 6470000000 | J7: 0 | K7: 0 | L7: 8.7470769e+09 | M7: 5.6212333e+08 | N7: 6470000000 | O7: 7718000000 | P7: 0 | Q7: 27013.309 | R7: 491.3893 | S7: 0 | T7: 47227.713 | U7: 0 | V7: 26511.495 | W7: 2948.3359 | X7: 39590.995 | Y7: 0 | Z7: 0 | AA7: 53524.804 | AB7: 3439.7252 | AC7: 39590.995 | AD7: 47227.713 | AE7: 0 | AF7: 69888.14 | AG7: 163421 | AH7: 160606.67 | AI7: 193735000 | AJ7: 97500000 | AK7: 55533333 | AL7: 48281287 | AM7: 25900000 | AN7: 61610000 | AO7: 27533549 | AP7: 19140567 | AQ7: 2588 | AR7: 190553.33 | AS7: 5010
A8: 46063 | B8: 4563195540 | C8: 81483000 | D8: 0 | E8: 7718000000 | F8: 0 | G8: 4465805000 | H8: 488898000 | I8: 6305000000 | J8: 0 | K8: 0 | L8: 9029000540 | M8: 570381000 | N8: 6305000000 | O8: 7718000000 | P8: 0 | Q8: 27660.424 | R8: 493.9202 | S8: 0 | T8: 46783.697 | U8: 0 | V8: 27070.079 | W8: 2963.5211 | X8: 38218.607 | Y8: 0 | Z8: 0 | AA8: 54730.503 | AB8: 3457.4413 | AC8: 38218.607 | AD8: 46783.697 | AE8: 0 | AF8: 69115.728 | AG8: 164972 | AH8: 162966 | AI8: 199699000 | AJ8: 101366000 | AK8: 56920000 | AL8: 49486870 | AM8: 25900000 | AN8: 61610000 | AO8: 27500000 | AP8: 19924320 | AQ8: 2522 | AR8: 194104 | AS8: 5045.6
A9: 46064 | B9: 4567114746 | C9: 81620000 | D9: 0 | E9: 7718000000 | F9: 0 | G9: 4472420000 | H9: 489720000 | I9: 6300000000 | J9: 0 | K9: 0 | L9: 9039534746 | M9: 571340000 | N9: 6300000000 | O9: 7718000000 | P9: 0 | Q9: 27600.529 | R9: 493.2557 | S9: 0 | T9: 46642.332 | U9: 0 | V9: 27028.259 | W9: 2959.5339 | X9: 38072.907 | Y9: 0 | Z9: 0 | AA9: 54628.788 | AB9: 3452.7896 | AC9: 38072.907 | AD9: 46642.332 | AE9: 0 | AF9: 67067.963 | AG9: 165472 | AH9: 163240 | AI9: 200010000 | AJ9: 101720000 | AK9: 56830000 | AL9: 49408623 | AM9: 25900000 | AN9: 61610000 | AO9: 27500000 | AP9: 19951500 | AQ9: 2520 | AR9: 194410 | AS9: 5068
A10: 46065 | B10: 4.4818125e+09 | C10: 81145000 | D10: 0 | E10: 7718000000 | F10: 0 | G10: 4393588750 | H10: 486870000 | I10: 6300000000 | J10: 0 | K10: 0 | L10: 8.8754013e+09 | M10: 568015000 | N10: 6300000000 | O10: 7718000000 | P10: 0 | Q10: 27322.461 | R10: 494.684 | S10: 0 | T10: 47051.221 | U10: 0 | V10: 26784.622 | W10: 2968.1042 | X10: 38406.672 | Y10: 0 | Z10: 0 | AA10: 54107.083 | AB10: 3462.7882 | AC10: 38406.672 | AD10: 47051.221 | AE10: 0 | AF10: 66979.535 | AG10: 164034 | AH10: 162290 | AI10: 196503750 | AJ10: 99182500 | AK10: 55942500 | AL10: 48637021 | AM10: 25900000 | AN10: 61610000 | AO10: 27500000 | AP10: 19508150 | AQ10: 2520 | AR10: 192852.5 | AS10: 5035.25
A11: 46066 | B11: 4482492878 | C11: 81275000 | D11: 0 | E11: 7718000000 | F11: 0 | G11: 4381530000 | H11: 487650000 | I11: 6300000000 | J11: 0 | K11: 0 | L11: 8864022878 | M11: 568925000 | N11: 6300000000 | O11: 7718000000 | P11: 0 | Q11: 27480.4 | R11: 498.265 | S11: 0 | T11: 47316.02 | U11: 0 | V11: 26861.436 | W11: 2989.5902 | X11: 38622.821 | Y11: 0 | Z11: 0 | AA11: 54341.836 | AB11: 3487.8553 | AC11: 38622.821 | AD11: 47316.02 | AE11: 0 | AF11: 67727.465 | AG11: 163116 | AH11: 162550 | AI11: 195990000 | AJ11: 98640000 | AK11: 55700000 | AL11: 48426189 | AM11: 25900000 | AN11: 61610000 | AO11: 27500000 | AP11: 19529700 | AQ11: 2520 | AR11: 193130 | AS11: 4989
A12: 46067 | B12: 4315003130 | C12: 79312500 | D12: 0 | E12: 7718000000 | F12: 0 | G12: 4270507500 | H12: 475875000 | I12: 6125000000 | J12: 0 | K12: 0 | L12: 8585510630 | M12: 555187500 | N12: 6125000000 | O12: 7718000000 | P12: 0 | Q12: 26807.089 | R12: 492.7313 | S12: 0 | T12: 47948.312 | U12: 0 | V12: 26530.659 | W12: 2956.388 | X12: 38051.75 | Y12: 0 | Z12: 0 | AA12: 53337.748 | AB12: 3449.1194 | AC12: 38051.75 | AD12: 47948.312 | AE12: 0 | AF12: 69627.01 | AG12: 160965 | AH12: 158625 | AI12: 190997500 | AJ12: 97560000 | AK12: 54000000 | AL12: 46948190 | AM12: 25900000 | AN12: 61610000 | AO12: 26500000 | AP12: 18669450 | AQ12: 2450 | AR12: 188355 | AS12: 5043
A13: 46068 | B13: 4380975133 | C13: 79704375 | D13: 0 | E13: 7718000000 | F13: 0 | G13: 4340173750 | H13: 478226250 | I13: 6119375000 | J13: 0 | K13: 0 | L13: 8721148883 | M13: 557930625 | N13: 6119375000 | O13: 7718000000 | P13: 0 | Q13: 27297.666 | R13: 496.6345 | S13: 0 | T13: 48090.523 | U13: 0 | V13: 27043.434 | W13: 2979.807 | X13: 38129.56 | Y13: 0 | Z13: 0 | AA13: 54341.101 | AB13: 3476.4415 | AC13: 38129.56 | AD13: 48090.523 | AE13: 0 | AF13: 69855.085 | AG13: 160489 | AH13: 159408.75 | AI13: 194118750 | AJ13: 98695000 | AK13: 54995000 | AL13: 47813254 | AM13: 25900000 | AN13: 61610000 | AO13: 26750000 | AP13: 18985575 | AQ13: 2447.75 | AR13: 189285 | AS13: 5043
... A115: 46221 | B115: 4351819789 | C115: 96590000 | D115: 0 | E115: 7718000000 | F115: 0 | G115: 4214058750 | H115: 579540000 | I115: 7017500000 | J115: 0 | K115: 0 | L115: 8565878539 | M115: 676130000 | N115: 7017500000 | O115: 7718000000 | P115: 0 | Q115: 22534.392 | R115: 500.1582 | S115: 0 | T115: 39965.083 | U115: 0 | V115: 21821.077 | W115: 3000.949 | X115: 36337.777 | Y115: 0 | Z115: 0 | AA115: 44355.469 | AB115: 3501.1072 | AC115: 36337.777 | AD115: 39965.083 | AE115: 0 | AF115: 64060 | AG115: 193119 | AH115: 193180 | AI115: 188376250 | AJ115: 95797500 | AK115: 54120000 | AL115: 47052520 | AM115: 25900000 | AN115: 61610000 | AO115: 28500000 | AP115: 18852900 | AQ115: 2807 | AR115: 221452.5 | AS115: 4017

Sheet Live_Data
A1: Asset | B1: Price | C1: Unit | D1: Price Key | E1: Last Snapshot
A2: Bitcoin | B2: 64018 | C2: USD | D2: bitcoin_usd | E2: 2026-07-18T16:48:34.642516
A3: Tether | B3: 193400 | C3: IRT | D3: usdt_irt | E3: 2026-07-18T16:48:34.642516
A4: US Dollar | B4: 193400 | C4: IRT | D4: usd_cash | E4: 2026-07-18T16:48:34.642516
A5: Emami Coin | B5: 188510000 | C5: IRT | D5: emami_coin | E5: 2026-07-18T16:48:34.642516
A6: Half Coin | B6: 95940000 | C6: IRT | D6: half_coin | E6: 2026-07-18T16:48:34.642516
A7: Quarter Coin | B7: 54060000 | C7: IRT | D7: quarter_coin | E7: 2026-07-18T16:48:34.642516
A8: Quarter Coin (Pre-86) | B8: 47000355 | C8: IRT | D8: quarter_coin_pre86 | E8: 2026-07-18T16:48:34.642516
A9: Swiss Gold Bar (1g) | B9: 25900000 | C9: IRT | D9: swiss_gold_bar_1g | E9: 2026-07-18T16:48:34.642516
A10: Swiss Gold Bar (2.5g) | B10: 61610000 | C10: IRT | D10: swiss_gold_bar_2_5g | E10: 2026-07-18T16:48:34.642516
A11: 1g Coin | B11: 28500000 | C11: IRT | D11: one_gram_coin | E11: 2026-07-18T16:48:34.642516
A12: Gold Gram (18K) | B12: 18894900 | C12: IRT | D12: gold_18k_gram | E12: 2026-07-18T16:48:34.642516
A13: KAMA Stock | B13: 2807 | C13: IRT | D13: kama_stock | E13: 2026-07-18T16:48:34.642516
... A15: Gold Ounce (Global) | B15: 4017 | C15: USD | D15: gold_ounce_usd | E15: 2026-07-18T16:48:34.642516

Sheet Allocation
A1: Currency | B1: Owner | C1: Asset Class | D1: Value | E1: Share
A2: IRT | B2: Mother | C2: Gold | D2: 4358299210 | E2: =IFERROR(D2/SUMIFS(D:D,A:A,A2,B:B,B2),0)
A3: IRT | B3: Mother | C3: Cash | D3: 96700000 | E3: =IFERROR(D3/SUMIFS(D:D,A:A,A3,B:B,B3),0)
A4: IRT | B4: Mother | C4: Stock | D4: 0 | E4: =IFERROR(D4/SUMIFS(D:D,A:A,A4,B:B,B4),0)
A5: IRT | B5: Mother | C5: Real Estate | D5: 7718000000 | E5: =IFERROR(D5/SUMIFS(D:D,A:A,A5,B:B,B5),0)
A6: IRT | B6: Mother | C6: Crypto | D6: 0 | E6: =IFERROR(D6/SUMIFS(D:D,A:A,A6,B:B,B6),0)
A7: IRT | B7: Father | C7: Gold | D7: 4216830000 | E7: =IFERROR(D7/SUMIFS(D:D,A:A,A7,B:B,B7),0)
A8: IRT | B8: Father | C8: Cash | D8: 580200000 | E8: =IFERROR(D8/SUMIFS(D:D,A:A,A8,B:B,B8),0)
A9: IRT | B9: Father | C9: Stock | D9: 7017500000 | E9: =IFERROR(D9/SUMIFS(D:D,A:A,A9,B:B,B9),0)
A10: IRT | B10: Father | C10: Real Estate | D10: 0 | E10: =IFERROR(D10/SUMIFS(D:D,A:A,A10,B:B,B10),0)
A11: IRT | B11: Father | C11: Crypto | D11: 0 | E11: =IFERROR(D11/SUMIFS(D:D,A:A,A11,B:B,B11),0)
A12: IRT | B12: Total | C12: Gold | D12: 8575129210 | E12: =IFERROR(D12/SUMIFS(D:D,A:A,A12,B:B,B12),0)
A13: IRT | B13: Total | C13: Cash | D13: 676900000 | E13: =IFERROR(D13/SUMIFS(D:D,A:A,A13,B:B,B13),0)
... A31: USD | B31: Total | C31: Crypto | D31: 0 | E31: =IFERROR(D31/SUMIFS(D:D,A:A,A31,B:B,B31),0)

Sheet Trends
A1: Date | B1: Total IRT | C1: Total USD | D1: Mother IRT | E1: Father IRT | F1: Gold IRT | G1: Cash IRT | H1: Stock IRT | I1: Real Estate IRT | J1: Crypto IRT
A2: =History_Data!A2 | B2: =History_Data!L2+History_Data!M2+History_Data!N2+History_Data!O2+History_Data!P2 | C2: =History_Data!AA2+History_Data!AB2+History_Data!AC2+History_Data!AD2+History_Data!AE2 | D2: =History_Data!B2+History_Data!C2+History_Data!D2+History_Data!E2+History_Data!F2 | E2: =History_Data!G2+History_Data!H2+History_Data!I2+History_Data!J2+History_Data!K2 | F2: =History_Data!L2 | G2: =History_Data!M2 | H2: =History_Data!N2 | I2: =History_Data!O2 | J2: =History_Data!P2
A3: =History_Data!A3 | B3: =History_Data!L3+History_Data!M3+History_Data!N3+History_Data!O3+History_Data!P3 | C3: =History_Data!AA3+History_Data!AB3+History_Data!AC3+History_Data!AD3+History_Data!AE3 | D3: =History_Data!B3+History_Data!C3+History_Data!D3+History_Data!E3+History_Data!F3 | E3: =History_Data!G3+History_Data!H3+History_Data!I3+History_Data!J3+History_Data!K3 | F3: =History_Data!L3 | G3: =History_Data!M3 | H3: =History_Data!N3 | I3: =History_Data!O3 | J3: =History_Data!P3
A4: =History_Data!A4 | B4: =History_Data!L4+History_Data!M4+History_Data!N4+History_Data!O4+History_Data!P4 | C4: =History_Data!AA4+History_Data!AB4+History_Data!AC4+History_Data!AD4+History_Data!AE4 | D4: =History_Data!B4+History_Data!C4+History_Data!D4+History_Data!E4+History_Data!F4 | E4: =History_Data!G4+History_Data!H4+History_Data!I4+History_Data!J4+History_Data!K4 | F4: =History_Data!L4 | G4: =History_Data!M4 | H4: =History_Data!N4 | I4: =History_Data!O4 | J4: =History_Data!P4
A5: =History_Data!A5 | B5: =History_Data!L5+History_Data!M5+History_Data!N5+History_Data!O5+History_Data!P5 | C5: =History_Data!AA5+History_Data!AB5+History_Data!AC5+History_Data!AD5+History_Data!AE5 | D5: =History_Data!B5+History_Data!C5+History_Data!D5+History_Data!E5+History_Data!F5 | E5: =History_Data!G5+History_Data!H5+History_Data!I5+History_Data!J5+History_Data!K5 | F5: =History_Data!L5 | G5: =History_Data!M5 | H5: =History_Data!N5 | I5: =History_Data!O5 | J5: =History_Data!P5
A6: =History_Data!A6 | B6: =History_Data!L6+History_Data!M6+History_Data!N6+History_Data!O6+History_Data!P6 | C6: =History_Data!AA6+History_Data!AB6+History_Data!AC6+History_Data!AD6+History_Data!AE6 | D6: =History_Data!B6+History_Data!C6+History_Data!D6+History_Data!E6+History_Data!F6 | E6: =History_Data!G6+History_Data!H6+History_Data!I6+History_Data!J6+History_Data!K6 | F6: =History_Data!L6 | G6: =History_Data!M6 | H6: =History_Data!N6 | I6: =History_Data!O6 | J6: =History_Data!P6
A7: =History_Data!A7 | B7: =History_Data!L7+History_Data!M7+History_Data!N7+History_Data!O7+History_Data!P7 | C7: =History_Data!AA7+History_Data!AB7+History_Data!AC7+History_Data!AD7+History_Data!AE7 | D7: =History_Data!B7+History_Data!C7+History_Data!D7+History_Data!E7+History_Data!F7 | E7: =History_Data!G7+History_Data!H7+History_Data!I7+History_Data!J7+History_Data!K7 | F7: =History_Data!L7 | G7: =History_Data!M7 | H7: =History_Data!N7 | I7: =History_Data!O7 | J7: =History_Data!P7
A8: =History_Data!A8 | B8: =History_Data!L8+History_Data!M8+History_Data!N8+History_Data!O8+History_Data!P8 | C8: =History_Data!AA8+History_Data!AB8+History_Data!AC8+History_Data!AD8+History_Data!AE8 | D8: =History_Data!B8+History_Data!C8+History_Data!D8+History_Data!E8+History_Data!F8 | E8: =History_Data!G8+History_Data!H8+History_Data!I8+History_Data!J8+History_Data!K8 | F8: =History_Data!L8 | G8: =History_Data!M8 | H8: =History_Data!N8 | I8: =History_Data!O8 | J8: =History_Data!P8
A9: =History_Data!A9 | B9: =History_Data!L9+History_Data!M9+History_Data!N9+History_Data!O9+History_Data!P9 | C9: =History_Data!AA9+History_Data!AB9+History_Data!AC9+History_Data!AD9+History_Data!AE9 | D9: =History_Data!B9+History_Data!C9+History_Data!D9+History_Data!E9+History_Data!F9 | E9: =History_Data!G9+History_Data!H9+History_Data!I9+History_Data!J9+History_Data!K9 | F9: =History_Data!L9 | G9: =History_Data!M9 | H9: =History_Data!N9 | I9: =History_Data!O9 | J9: =History_Data!P9
A10: =History_Data!A10 | B10: =History_Data!L10+History_Data!M10+History_Data!N10+History_Data!O10+History_Data!P10 | C10: =History_Data!AA10+History_Data!AB10+History_Data!AC10+History_Data!AD10+History_Data!AE10 | D10: =History_Data!B10+History_Data!C10+History_Data!D10+History_Data!E10+History_Data!F10 | E10: =History_Data!G10+History_Data!H10+History_Data!I10+History_Data!J10+History_Data!K10 | F10: =History_Data!L10 | G10: =History_Data!M10 | H10: =History_Data!N10 | I10: =History_Data!O10 | J10: =History_Data!P10
A11: =History_Data!A11 | B11: =History_Data!L11+History_Data!M11+History_Data!N11+History_Data!O11+History_Data!P11 | C11: =History_Data!AA11+History_Data!AB11+History_Data!AC11+History_Data!AD11+History_Data!AE11 | D11: =History_Data!B11+History_Data!C11+History_Data!D11+History_Data!E11+History_Data!F11 | E11: =History_Data!G11+History_Data!H11+History_Data!I11+History_Data!J11+History_Data!K11 | F11: =History_Data!L11 | G11: =History_Data!M11 | H11: =History_Data!N11 | I11: =History_Data!O11 | J11: =History_Data!P11
A12: =History_Data!A12 | B12: =History_Data!L12+History_Data!M12+History_Data!N12+History_Data!O12+History_Data!P12 | C12: =History_Data!AA12+History_Data!AB12+History_Data!AC12+History_Data!AD12+History_Data!AE12 | D12: =History_Data!B12+History_Data!C12+History_Data!D12+History_Data!E12+History_Data!F12 | E12: =History_Data!G12+History_Data!H12+History_Data!I12+History_Data!J12+History_Data!K12 | F12: =History_Data!L12 | G12: =History_Data!M12 | H12: =History_Data!N12 | I12: =History_Data!O12 | J12: =History_Data!P12
A13: =History_Data!A13 | B13: =History_Data!L13+History_Data!M13+History_Data!N13+History_Data!O13+History_Data!P13 | C13: =History_Data!AA13+History_Data!AB13+History_Data!AC13+History_Data!AD13+History_Data!AE13 | D13: =History_Data!B13+History_Data!C13+History_Data!D13+History_Data!E13+History_Data!F13 | E13: =History_Data!G13+History_Data!H13+History_Data!I13+History_Data!J13+History_Data!K13 | F13: =History_Data!L13 | G13: =History_Data!M13 | H13: =History_Data!N13 | I13: =History_Data!O13 | J13: =History_Data!P13
... A115: =History_Data!A115 | B115: =History_Data!L115+History_Data!M115+History_Data!N115+History_Data!O115+History_Data!P115 | C115: =History_Data!AA115+History_Data!AB115+History_Data!AC115+History_Data!AD115+History_Data!AE115 | D115: =History_Data!B115+History_Data!C115+History_Data!D115+History_Data!E115+History_Data!F115 | E115: =History_Data!G115+History_Data!H115+History_Data!I115+History_Data!J115+History_Data!K115 | F115: =History_Data!L115 | G115: =History_Data!M115 | H115: =History_Data!N115 | I115: =History_Data!O115 | J115: =History_Data!P115

Sheet Comparison
A1: What-If Lump-Sum Comparison
A3: Start Date | B3: =Settings!B3
A4: Investment Amount | B4: =Settings!B4
A5: Actual Portfolio Total (IRT) | B5: =Dashboard!B4
A8: Asset | B8: Price Key | C8: Start Price | D8: Latest Price | E8: Units Bought | F8: Current Value | G8: Return %
A9: Bitcoin | B9: bitcoin_usd | C9: =IFERROR(XLOOKUP($B$3,History_Data!$A$2:$A$115,History_Data!$B$2:$B$115,"",1),"") | D9: 64018 | E9: =IFERROR($B$4/C9,0) | F9: =IFERROR(E9*D9,0) | G9: =IFERROR(F9/$B$4-1,0)
A10: Tether | B10: usdt_irt | C10: =IFERROR(XLOOKUP($B$3,History_Data!$A$2:$A$115,History_Data!$C$2:$C$115,"",1),"") | D10: 193400 | E10: =IFERROR($B$4/C10,0) | F10: =IFERROR(E10*D10,0) | G10: =IFERROR(F10/$B$4-1,0)
A11: US Dollar | B11: usd_cash | C11: =IFERROR(XLOOKUP($B$3,History_Data!$A$2:$A$115,History_Data!$D$2:$D$115,"",1),"") | D11: 193400 | E11: =IFERROR($B$4/C11,0) | F11: =IFERROR(E11*D11,0) | G11: =IFERROR(F11/$B$4-1,0)
A12: Emami Coin | B12: emami_coin | C12: =IFERROR(XLOOKUP($B$3,History_Data!$A$2:$A$115,History_Data!$E$2:$E$115,"",1),"") | D12: 188510000 | E12: =IFERROR($B$4/C12,0) | F12: =IFERROR(E12*D12,0) | G12: =IFERROR(F12/$B$4-1,0)
A13: Half Coin | B13: half_coin | C13: =IFERROR(XLOOKUP($B$3,History_Data!$A$2:$A$115,History_Data!$F$2:$F$115,"",1),"") | D13: 95940000 | E13: =IFERROR($B$4/C13,0) | F13: =IFERROR(E13*D13,0) | G13: =IFERROR(F13/$B$4-1,0)
A14: Quarter Coin | B14: quarter_coin | C14: =IFERROR(XLOOKUP($B$3,History_Data!$A$2:$A$115,History_Data!$G$2:$G$115,"",1),"") | D14: 54060000 | E14: =IFERROR($B$4/C14,0) | F14: =IFERROR(E14*D14,0) | G14: =IFERROR(F14/$B$4-1,0)
A15: Quarter Coin (Pre-86) | B15: quarter_coin_pre86 | C15: =IFERROR(XLOOKUP($B$3,History_Data!$A$2:$A$115,History_Data!$H$2:$H$115,"",1),"") | D15: 47000355 | E15: =IFERROR($B$4/C15,0) | F15: =IFERROR(E15*D15,0) | G15: =IFERROR(F15/$B$4-1,0)
A16: Swiss Gold Bar (1g) | B16: swiss_gold_bar_1g | C16: =IFERROR(XLOOKUP($B$3,History_Data!$A$2:$A$115,History_Data!$I$2:$I$115,"",1),"") | D16: 25900000 | E16: =IFERROR($B$4/C16,0) | F16: =IFERROR(E16*D16,0) | G16: =IFERROR(F16/$B$4-1,0)
A17: Swiss Gold Bar (2.5g) | B17: swiss_gold_bar_2_5g | C17: =IFERROR(XLOOKUP($B$3,History_Data!$A$2:$A$115,History_Data!$J$2:$J$115,"",1),"") | D17: 61610000 | E17: =IFERROR($B$4/C17,0) | F17: =IFERROR(E17*D17,0) | G17: =IFERROR(F17/$B$4-1,0)
A18: 1g Coin | B18: one_gram_coin | C18: =IFERROR(XLOOKUP($B$3,History_Data!$A$2:$A$115,History_Data!$K$2:$K$115,"",1),"") | D18: 28500000 | E18: =IFERROR($B$4/C18,0) | F18: =IFERROR(E18*D18,0) | G18: =IFERROR(F18/$B$4-1,0)
A19: Gold Gram (18K) | B19: gold_18k_gram | C19: =IFERROR(XLOOKUP($B$3,History_Data!$A$2:$A$115,History_Data!$L$2:$L$115,"",1),"") | D19: 18894900 | E19: =IFERROR($B$4/C19,0) | F19: =IFERROR(E19*D19,0) | G19: =IFERROR(F19/$B$4-1,0)
A20: KAMA Stock | B20: kama_stock | C20: =IFERROR(XLOOKUP($B$3,History_Data!$A$2:$A$115,History_Data!$M$2:$M$115,"",1),"") | D20: 2807 | E20: =IFERROR($B$4/C20,0) | F20: =IFERROR(E20*D20,0) | G20: =IFERROR(F20/$B$4-1,0)
A21: Euro | B21: euro_cash | C21: =IFERROR(XLOOKUP($B$3,History_Data!$A$2:$A$115,History_Data!$N$2:$N$115,"",1),"") | D21: 221780 | E21: =IFERROR($B$4/C21,0) | F21: =IFERROR(E21*D21,0) | G21: =IFERROR(F21/$B$4-1,0)
A22: Gold Ounce (Global) | B22: gold_ounce_usd | C22: =IFERROR(XLOOKUP($B$3,History_Data!$A$2:$A$115,History_Data!$O$2:$O$115,"",1),"") | D22: 4017 | E22: =IFERROR($B$4/C22,0) | F22: =IFERROR(E22*D22,0) | G22: =IFERROR(F22/$B$4-1,0)
